kgcpy/__init__.py
kgcpy/df_quantile.csv
kgcpy/kg_zoneNum.csv
kgcpy/kgcities.csv
kgcpy/kmz_int_reshape.png
kgcpy/test_functions.py
kgcpy/zipcodes.csv
kgcpy-1.1.8.dist-info/LICENSE.txt
kgcpy-1.1.8.dist-info/METADATA
kgcpy-1.1.8.dist-info/WHEEL
kgcpy-1.1.8.dist-info/top_level.txt
kgcpy-1.1.8.dist-info/RECORD
