Metadata-Version: 2.1
Name: kgcpy
Version: 1.1.8
Summary: Aids in identifying the Koeppen-Geiger (KG) climatic zone for a given latitude and longitude of any location.
Author-email: Xuanji Yu <xuanjiy@bu.edu>, Chelsey Bryant <clb117@case.edu>, "Nicholas R. Wheeler" <nrw16@case.edu>, Franz Rubel <franz.rubel@vetmeduni.ac.at>, Julian Ascencio Vasquez <julian.ascencio@envision-digital.com>, "Roger H. French" <rxf131@case.edu>
Project-URL: Bug Tracker, https://github.com/cwru-sdle/kgcpy/issues
Project-URL: Source Code, https://github.com/cwru-sdle/kgcpy
Project-URL: Documentation, https://kgcpy.readthedocs.io
Classifier: Development Status :: 4 - Beta
Classifier: License :: OSI Approved :: BSD License
Classifier: Operating System :: OS Independent
Classifier: Intended Audience :: Science/Research
Classifier: Programming Language :: Python
Classifier: Programming Language :: Python :: 3
Classifier: Topic :: Scientific/Engineering
Requires-Python: >=3.9
License-File: LICENSE.txt
Requires-Dist: pillow
Requires-Dist: pandas
Provides-Extra: test
Requires-Dist: pytest ; extra == 'test'
